hiplot_mlflow.py
hiplot_mlflow-0.1.0.dist-info/LICENSE-2.0.txt
hiplot_mlflow-0.1.0.dist-info/METADATA
hiplot_mlflow-0.1.0.dist-info/WHEEL
hiplot_mlflow-0.1.0.dist-info/top_level.txt
hiplot_mlflow-0.1.0.dist-info/RECORD
