Metadata-Version: 2.1
Name: hiplot-mlflow
Version: 0.1.0
Summary: HiPlot fetcher plugin for MLflow experiment tracking.
Home-page: https://github.com/facultyai/hiplot-mlflow
Author: Faculty
Author-email: opensource@faculty.ai
License: Apache Software License
Platform: UNKNOWN
Requires-Dist: hiplot
Requires-Dist: mlflow
Requires-Dist: numpy
Provides-Extra: dev
Requires-Dist: black ; extra == 'dev'
Requires-Dist: flake8 ; extra == 'dev'
Requires-Dist: flake8-black ; extra == 'dev'
Requires-Dist: mypy ; extra == 'dev'
Requires-Dist: pytest ; extra == 'dev'
Requires-Dist: tox ; extra == 'dev'
